{"itemNbr": 101416462, "stores": [{"storeNbr": 1124, "storeName": "BA CORALES", "storeType": "BASE STR CF Bodega", "formato": "BODEGA", "whseNbr": 4188, "onHand": 0, "inTransit": 0, "inWhse": 0, "onOrder": 30, "promDia": 0.52, "doh": 0.0, "agotado": 1, "falta1d": 1, "falta3d": 1, "falta7d": 1, "venta8sem": 29, "resurtible": "1"}, {"storeNbr": 1006, "storeName": "BA HOSPITAL GENERAL", "storeType": "BASE STR CF Bodega", "formato": "BODEGA", "whseNbr": 7487, "onHand": 0, "inTransit": 6, "inWhse": 0, "onOrder": 6, "promDia": 0.23, "doh": 0.0, "agotado": 1, "falta1d": 1, "falta3d": 1, "falta7d": 1, "venta8sem": 13, "resurtible": "1"}, {"storeNbr": 2466, "storeName": "SC CUITLAHUAC", "storeType": "BASE STR Supercenter", "formato": "SUPERCENTER", "whseNbr": 7464, "onHand": 0, "inTransit": 0, "inWhse": 0, "onOrder": 12, "promDia": 0.23, "doh": 0.0, "agotado": 1, "falta1d": 1, "falta3d": 1, "falta7d": 1, "venta8sem": 13, "resurtible": "1"}, {"storeNbr": 3226, "storeName": "BA ENSENADA", "storeType": "BASE STR CF Bodega", "formato": "BODEGA", "whseNbr": 4924, "onHand": 0, "inTransit": 0, "inWhse": 0, "onOrder": 12, "promDia": 0.18, "doh": 0.0, "agotado": 1, "falta1d": 1, "falta3d": 1, "falta7d": 1, "venta8sem": 10, "resurtible": "1"}, {"storeNbr": 2432, "storeName": "SC DURANGO", "storeType": "BASE STR Supercenter", "formato": "SUPERCENTER", "whseNbr": 7487, "onHand": 0, "inTransit": 6, "inWhse": 0, "onOrder": 6, "promDia": 0.14, "doh": 0.0, "agotado": 1, "falta1d": 1, "falta3d": 1, "falta7d": 1, "venta8sem": 8, "resurtible": "1"}, {"storeNbr": 2955, "storeName": "MB TANGANCICUARO", "storeType": "BASE STR CF Bodega", "formato": "MIBODEGA", "whseNbr": 5907, "onHand": 0, "inTransit": 0, "inWhse": 0, "onOrder": 12, "promDia": 0.12, "doh": 0.0, "agotado": 1, "falta1d": 1, "falta3d": 1, "falta7d": 1, "venta8sem": 7, "resurtible": "1"}, {"storeNbr": 3001, "storeName": "BA CORDOBA AV 11", "storeType": "BASE STR CF Bodega", "formato": "BODEGA", "whseNbr": 7468, "onHand": 0, "inTransit": 0, "inWhse": 6, "onOrder": 6, "promDia": 0.12, "doh": 0.0, "agotado": 1, "falta1d": 1, "falta3d": 1, "falta7d": 1, "venta8sem": 7, "resurtible": "1"}, {"storeNbr": 1927, "storeName": "BA PUERTA DEL SOL REAPERT", "storeType": "BASE STR CF Bodega", "formato": "BODEGA", "whseNbr": 7490, "onHand": 0, "inTransit": 0, "inWhse": 0, "onOrder": 0, "promDia": 0.11, "doh": 0.0, "agotado": 1, "falta1d": 1, "falta3d": 1, "falta7d": 1, "venta8sem": 6, "resurtible": "1"}, {"storeNbr": 3067, "storeName": "BA SALINA CRUZ", "storeType": "BASE STR CF Bodega", "formato": "BODEGA", "whseNbr": 7468, "onHand": 0, "inTransit": 0, "inWhse": 6, "onOrder": 6, "promDia": 0.11, "doh": 0.0, "agotado": 1, "falta1d": 1, "falta3d": 1, "falta7d": 1, "venta8sem": 6, "resurtible": "1"}, {"storeNbr": 3666, "storeName": "BA XALAPA", "storeType": "BASE STR CF Bodega", "formato": "BODEGA", "whseNbr": 7471, "onHand": 0, "inTransit": 0, "inWhse": 0, "onOrder": 6, "promDia": 0.11, "doh": 0.0, "agotado": 1, "falta1d": 1, "falta3d": 1, "falta7d": 1, "venta8sem": 6, "resurtible": "1"}, {"storeNbr": 4650, "storeName": "MB JUCHIPILA NORTE", "storeType": "BASE STR CF Bodega", "formato": "MIBODEGA", "whseNbr": 5907, "onHand": 0, "inTransit": 0, "inWhse": 0, "onOrder": 6, "promDia": 0.11, "doh": 0.0, "agotado": 1, "falta1d": 1, "falta3d": 1, "falta7d": 1, "venta8sem": 6, "resurtible": "1"}, {"storeNbr": 3114, "storeName": "SC CUMBRES MONTERREY", "storeType": "BASE STR Supercenter", "formato": "SUPERCENTER", "whseNbr": 7490, "onHand": 0, "inTransit": 0, "inWhse": 0, "onOrder": 6, "promDia": 0.09, "doh": 0.0, "agotado": 1, "falta1d": 1, "falta3d": 1, "falta7d": 1, "venta8sem": 5, "resurtible": "1"}, {"storeNbr": 4045, "storeName": "BA LOMAS DEL BOSQUE", "storeType": "BASE STR CF Bodega", "formato": "BODEGA", "whseNbr": 7490, "onHand": 0, "inTransit": 0, "inWhse": 0, "onOrder": 12, "promDia": 0.09, "doh": 0.0, "agotado": 1, "falta1d": 1, "falta3d": 1, "falta7d": 1, "venta8sem": 5, "resurtible": "1"}, {"storeNbr": 5712, "storeName": "BA SOLIDARIDAD", "storeType": "BASE STR CF Bodega", "formato": "BODEGA", "whseNbr": 7490, "onHand": 0, "inTransit": 0, "inWhse": 0, "onOrder": 12, "promDia": 0.09, "doh": 0.0, "agotado": 1, "falta1d": 1, "falta3d": 1, "falta7d": 1, "venta8sem": 5, "resurtible": "1"}, {"storeNbr": 1111, "storeName": "BA EL ALAMO", "storeType": "BASE STR CF Bodega", "formato": "BODEGA", "whseNbr": 7482, "onHand": 0, "inTransit": 0, "inWhse": 0, "onOrder": 12, "promDia": 0.07, "doh": 0.0, "agotado": 1, "falta1d": 1, "falta3d": 1, "falta7d": 1, "venta8sem": 4, "resurtible": "1"}, {"storeNbr": 1254, "storeName": "MB ACALA", "storeType": "BASE STR CF Bodega", "formato": "MIBODEGA", "whseNbr": 7468, "onHand": 0, "inTransit": 0, "inWhse": 6, "onOrder": 6, "promDia": 0.07, "doh": 0.0, "agotado": 1, "falta1d": 1, "falta3d": 1, "falta7d": 1, "venta8sem": 4, "resurtible": "1"}, {"storeNbr": 2548, "storeName": "BA AV UNIVERSIDAD", "storeType": "BASE STR CF Bodega", "formato": "BODEGA", "whseNbr": 7493, "onHand": 0, "inTransit": 0, "inWhse": 0, "onOrder": 0, "promDia": 0.07, "doh": 0.0, "agotado": 1, "falta1d": 1, "falta3d": 1, "falta7d": 1, "venta8sem": 4, "resurtible": ""}, {"storeNbr": 3720, "storeName": "SC LINCOLN", "storeType": "BASE STR Supercenter", "formato": "SUPERCENTER", "whseNbr": 7490, "onHand": 0, "inTransit": 0, "inWhse": 0, "onOrder": 6, "promDia": 0.07, "doh": 0.0, "agotado": 1, "falta1d": 1, "falta3d": 1, "falta7d": 1, "venta8sem": 4, "resurtible": "1"}, {"storeNbr": 1179, "storeName": "BA MORELIA NORTE III", "storeType": "BASE STR CF Bodega", "formato": "BODEGA", "whseNbr": 7494, "onHand": 0, "inTransit": 0, "inWhse": 6, "onOrder": 6, "promDia": 0.05, "doh": 0.0, "agotado": 1, "falta1d": 1, "falta3d": 1, "falta7d": 1, "venta8sem": 3, "resurtible": "1"}, {"storeNbr": 1517, "storeName": "BA SANTA ROSALIA", "storeType": "BASE STR CF Bodega", "formato": "BODEGA", "whseNbr": 4640, "onHand": 0, "inTransit": 0, "inWhse": 0, "onOrder": 0, "promDia": 0.05, "doh": 0.0, "agotado": 1, "falta1d": 1, "falta3d": 1, "falta7d": 1, "venta8sem": 3, "resurtible": "1"}, {"storeNbr": 1656, "storeName": "SC CLUB DE GOLF", "storeType": "BASE STR Supercenter", "formato": "SUPERCENTER", "whseNbr": 4640, "onHand": 0, "inTransit": 0, "inWhse": 0, "onOrder": 6, "promDia": 0.05, "doh": 0.0, "agotado": 1, "falta1d": 1, "falta3d": 1, "falta7d": 1, "venta8sem": 3, "resurtible": "1"}, {"storeNbr": 2000, "storeName": "BA MAZATLAN", "storeType": "BASE STR CF Bodega", "formato": "BODEGA", "whseNbr": 7487, "onHand": 0, "inTransit": 6, "inWhse": 0, "onOrder": 0, "promDia": 0.05, "doh": 0.0, "agotado": 1, "falta1d": 1, "falta3d": 1, "falta7d": 1, "venta8sem": 3, "resurtible": "1"}, {"storeNbr": 2018, "storeName": "MB SALVATIERRA", "storeType": "BASE STR CF Bodega", "formato": "MIBODEGA", "whseNbr": 8805, "onHand": 0, "inTransit": 0, "inWhse": 0, "onOrder": 0, "promDia": 0.05, "doh": 0.0, "agotado": 1, "falta1d": 1, "falta3d": 1, "falta7d": 1, "venta8sem": 3, "resurtible": "1"}, {"storeNbr": 2431, "storeName": "SC SAN LUIS POTOSI", "storeType": "BASE STR Supercenter", "formato": "SUPERCENTER", "whseNbr": 7490, "onHand": 0, "inTransit": 0, "inWhse": 0, "onOrder": 12, "promDia": 0.05, "doh": 0.0, "agotado": 1, "falta1d": 1, "falta3d": 1, "falta7d": 1, "venta8sem": 3, "resurtible": "1"}, {"storeNbr": 2868, "storeName": "BA JARDINES COLON", "storeType": "BASE STR CF Bodega", "formato": "BODEGA", "whseNbr": 7493, "onHand": 0, "inTransit": 6, "inWhse": 0, "onOrder": 0, "promDia": 0.05, "doh": 0.0, "agotado": 1, "falta1d": 1, "falta3d": 1, "falta7d": 1, "venta8sem": 3, "resurtible": "1"}, {"storeNbr": 3189, "storeName": "BD VILLARREAL", "storeType": "BASE STR CF Bodega", "formato": "BODEGA", "whseNbr": 7490, "onHand": 0, "inTransit": 0, "inWhse": 0, "onOrder": 6, "promDia": 0.05, "doh": 0.0, "agotado": 1, "falta1d": 1, "falta3d": 1, "falta7d": 1, "venta8sem": 3, "resurtible": "1"}, {"storeNbr": 3241, "storeName": "SC PLAZA DEL VALLE", "storeType": "BASE STR Supercenter", "formato": "SUPERCENTER", "whseNbr": 7468, "onHand": 0, "inTransit": 0, "inWhse": 6, "onOrder": 0, "promDia": 0.05, "doh": 0.0, "agotado": 1, "falta1d": 1, "falta3d": 1, "falta7d": 1, "venta8sem": 3, "resurtible": "1"}, {"storeNbr": 3431, "storeName": "MB PLAZA SAN DIEGO", "storeType": "BASE STR CF Bodega", "formato": "MIBODEGA", "whseNbr": 8805, "onHand": 0, "inTransit": 0, "inWhse": 0, "onOrder": 6, "promDia": 0.05, "doh": 0.0, "agotado": 1, "falta1d": 1, "falta3d": 1, "falta7d": 1, "venta8sem": 3, "resurtible": "1"}, {"storeNbr": 4093, "storeName": "MB JOCOTEPEC", "storeType": "BASE STR CF Bodega", "formato": "MIBODEGA", "whseNbr": 5907, "onHand": 0, "inTransit": 0, "inWhse": 0, "onOrder": 18, "promDia": 0.05, "doh": 0.0, "agotado": 1, "falta1d": 1, "falta3d": 1, "falta7d": 1, "venta8sem": 3, "resurtible": "1"}, {"storeNbr": 4639, "storeName": "BA MIRAMAR", "storeType": "BASE STR CF Bodega", "formato": "BODEGA", "whseNbr": 7487, "onHand": 0, "inTransit": 6, "inWhse": 0, "onOrder": 0, "promDia": 0.05, "doh": 0.0, "agotado": 1, "falta1d": 1, "falta3d": 1, "falta7d": 1, "venta8sem": 3, "resurtible": "1"}, {"storeNbr": 5055, "storeName": "SC CONCORDIA", "storeType": "BASE STR Supercenter", "formato": "SUPERCENTER", "whseNbr": 7490, "onHand": 0, "inTransit": 0, "inWhse": 0, "onOrder": 6, "promDia": 0.05, "doh": 0.0, "agotado": 1, "falta1d": 1, "falta3d": 1, "falta7d": 1, "venta8sem": 3, "resurtible": "1"}, {"storeNbr": 6339, "storeName": "BD CALZADA HEROES LAREDO", "storeType": "BASE STR CF Bodega", "formato": "BODEGA", "whseNbr": 7490, "onHand": 0, "inTransit": 0, "inWhse": 0, "onOrder": 6, "promDia": 0.05, "doh": 0.0, "agotado": 1, "falta1d": 1, "falta3d": 1, "falta7d": 1, "venta8sem": 3, "resurtible": "1"}, {"storeNbr": 6448, "storeName": "MB BALANCAN NORTE", "storeType": "BASE STR CF Bodega", "formato": "MIBODEGA", "whseNbr": 7468, "onHand": 0, "inTransit": 0, "inWhse": 6, "onOrder": 0, "promDia": 0.05, "doh": 0.0, "agotado": 1, "falta1d": 1, "falta3d": 1, "falta7d": 1, "venta8sem": 3, "resurtible": "1"}, {"storeNbr": 1082, "storeName": "BA TAPACHULA NORTE", "storeType": "BASE STR CF Bodega", "formato": "BODEGA", "whseNbr": 7468, "onHand": 0, "inTransit": 0, "inWhse": 6, "onOrder": 12, "promDia": 0.04, "doh": 0.0, "agotado": 1, "falta1d": 1, "falta3d": 1, "falta7d": 1, "venta8sem": 2, "resurtible": "1"}, {"storeNbr": 1174, "storeName": "BA MINATITLAN", "storeType": "BASE STR CF Bodega", "formato": "BODEGA", "whseNbr": 7468, "onHand": 0, "inTransit": 0, "inWhse": 6, "onOrder": 12, "promDia": 0.04, "doh": 0.0, "agotado": 1, "falta1d": 1, "falta3d": 1, "falta7d": 1, "venta8sem": 2, "resurtible": "1"}, {"storeNbr": 1194, "storeName": "MB IXTLAHUACA", "storeType": "BASE STR CF Bodega", "formato": "MIBODEGA", "whseNbr": 8805, "onHand": 0, "inTransit": 0, "inWhse": 0, "onOrder": 0, "promDia": 0.04, "doh": 0.0, "agotado": 1, "falta1d": 1, "falta3d": 1, "falta7d": 1, "venta8sem": 2, "resurtible": "1"}, {"storeNbr": 1553, "storeName": "BA HUINALA MONTERREY", "storeType": "BASE STR CF Bodega", "formato": "BODEGA", "whseNbr": 7490, "onHand": 0, "inTransit": 0, "inWhse": 0, "onOrder": 6, "promDia": 0.04, "doh": 0.0, "agotado": 1, "falta1d": 1, "falta3d": 1, "falta7d": 1, "venta8sem": 2, "resurtible": "1"}, {"storeNbr": 1560, "storeName": "BA J MARIANO JIMENEZ", "storeType": "BASE STR CF Bodega", "formato": "BODEGA", "whseNbr": 4640, "onHand": 0, "inTransit": 0, "inWhse": 0, "onOrder": 0, "promDia": 0.04, "doh": 0.0, "agotado": 1, "falta1d": 1, "falta3d": 1, "falta7d": 1, "venta8sem": 2, "resurtible": "1"}, {"storeNbr": 1651, "storeName": "MB OJO CALIENTE", "storeType": "BASE STR CF Bodega", "formato": "MIBODEGA", "whseNbr": 5907, "onHand": 0, "inTransit": 0, "inWhse": 0, "onOrder": 0, "promDia": 0.04, "doh": 0.0, "agotado": 1, "falta1d": 1, "falta3d": 1, "falta7d": 1, "venta8sem": 2, "resurtible": "1"}, {"storeNbr": 1943, "storeName": "BA FRAC MERIDA LS AMERICA", "storeType": "BASE STR CF Bodega", "formato": "BODEGA", "whseNbr": 4188, "onHand": 0, "inTransit": 0, "inWhse": 0, "onOrder": 12, "promDia": 0.04, "doh": 0.0, "agotado": 1, "falta1d": 1, "falta3d": 1, "falta7d": 1, "venta8sem": 2, "resurtible": "1"}, {"storeNbr": 2076, "storeName": "SC MIGUEL ALEMAN", "storeType": "BASE STR Supercenter", "formato": "SUPERCENTER", "whseNbr": 7490, "onHand": 0, "inTransit": 0, "inWhse": 0, "onOrder": 6, "promDia": 0.04, "doh": 0.0, "agotado": 1, "falta1d": 1, "falta3d": 1, "falta7d": 1, "venta8sem": 2, "resurtible": "1"}, {"storeNbr": 2141, "storeName": "BA XONACATLAN", "storeType": "BASE STR CF Bodega", "formato": "BODEGA", "whseNbr": 7494, "onHand": 0, "inTransit": 0, "inWhse": 0, "onOrder": 0, "promDia": 0.04, "doh": 0.0, "agotado": 1, "falta1d": 1, "falta3d": 1, "falta7d": 1, "venta8sem": 2, "resurtible": "1"}, {"storeNbr": 2332, "storeName": "MB TECOLUTILLA", "storeType": "BASE STR CF Bodega", "formato": "MIBODEGA", "whseNbr": 7468, "onHand": 0, "inTransit": 0, "inWhse": 6, "onOrder": 6, "promDia": 0.04, "doh": 0.0, "agotado": 1, "falta1d": 1, "falta3d": 1, "falta7d": 1, "venta8sem": 2, "resurtible": "1"}, {"storeNbr": 3550, "storeName": "MB SANTA FE", "storeType": "BASE STR CF Bodega", "formato": "MIBODEGA", "whseNbr": 5907, "onHand": 0, "inTransit": 0, "inWhse": 0, "onOrder": 12, "promDia": 0.04, "doh": 0.0, "agotado": 1, "falta1d": 1, "falta3d": 1, "falta7d": 1, "venta8sem": 2, "resurtible": "1"}, {"storeNbr": 3660, "storeName": "MB QUIROGA CENTRO", "storeType": "BASE STR CF Bodega", "formato": "MIBODEGA", "whseNbr": 5907, "onHand": 0, "inTransit": 0, "inWhse": 0, "onOrder": 12, "promDia": 0.04, "doh": 0.0, "agotado": 1, "falta1d": 1, "falta3d": 1, "falta7d": 1, "venta8sem": 2, "resurtible": "1"}, {"storeNbr": 5117, "storeName": "MB TEHUIXTLA", "storeType": "BASE STR CF Bodega", "formato": "MIBODEGA", "whseNbr": 7471, "onHand": 0, "inTransit": 6, "inWhse": 0, "onOrder": 0, "promDia": 0.04, "doh": 0.0, "agotado": 1, "falta1d": 1, "falta3d": 1, "falta7d": 1, "venta8sem": 2, "resurtible": "1"}, {"storeNbr": 5687, "storeName": "SC BOULEVARD DELTA", "storeType": "BASE STR Supercenter", "formato": "SUPERCENTER", "whseNbr": 7464, "onHand": 0, "inTransit": 0, "inWhse": 0, "onOrder": 12, "promDia": 0.04, "doh": 0.0, "agotado": 1, "falta1d": 1, "falta3d": 1, "falta7d": 1, "venta8sem": 2, "resurtible": "1"}, {"storeNbr": 6486, "storeName": "MB CINTALAPA OESTE", "storeType": "BASE STR CF Bodega", "formato": "MIBODEGA", "whseNbr": 7468, "onHand": 0, "inTransit": 0, "inWhse": 6, "onOrder": 0, "promDia": 0.04, "doh": 0.0, "agotado": 1, "falta1d": 1, "falta3d": 1, "falta7d": 1, "venta8sem": 2, "resurtible": "1"}, {"storeNbr": 1586, "storeName": "MB CIENEGA DE FLORES CENT", "storeType": "BASE STR CF Bodega", "formato": "MIBODEGA", "whseNbr": 5922, "onHand": 0, "inTransit": 0, "inWhse": 6, "onOrder": 0, "promDia": 0.02, "doh": 0.0, "agotado": 1, "falta1d": 1, "falta3d": 1, "falta7d": 1, "venta8sem": 1, "resurtible": "1"}, {"storeNbr": 1686, "storeName": "SC LA CIMA", "storeType": "BASE STR Supercenter", "formato": "SUPERCENTER", "whseNbr": 7493, "onHand": 0, "inTransit": 0, "inWhse": 6, "onOrder": 0, "promDia": 0.02, "doh": 0.0, "agotado": 1, "falta1d": 1, "falta3d": 1, "falta7d": 1, "venta8sem": 1, "resurtible": "1"}, {"storeNbr": 1813, "storeName": "MB OTUMBA", "storeType": "BASE STR CF Bodega", "formato": "MIBODEGA", "whseNbr": 8805, "onHand": 0, "inTransit": 0, "inWhse": 0, "onOrder": 6, "promDia": 0.02, "doh": 0.0, "agotado": 1, "falta1d": 1, "falta3d": 1, "falta7d": 1, "venta8sem": 1, "resurtible": "1"}, {"storeNbr": 2303, "storeName": "SC HERMOSILLO", "storeType": "BASE STR Supercenter", "formato": "SUPERCENTER", "whseNbr": 7487, "onHand": 0, "inTransit": 6, "inWhse": 0, "onOrder": 0, "promDia": 0.02, "doh": 0.0, "agotado": 1, "falta1d": 1, "falta3d": 1, "falta7d": 1, "venta8sem": 1, "resurtible": "1"}, {"storeNbr": 2952, "storeName": "BA SAN FCO TOTIMEHUACAN", "storeType": "BASE STR CF Bodega", "formato": "BODEGA", "whseNbr": 7471, "onHand": 0, "inTransit": 0, "inWhse": 0, "onOrder": 0, "promDia": 0.02, "doh": 0.0, "agotado": 1, "falta1d": 1, "falta3d": 1, "falta7d": 1, "venta8sem": 1, "resurtible": "1"}, {"storeNbr": 3056, "storeName": "BA SIGLO XXI", "storeType": "BASE STR CF Bodega", "formato": "BODEGA", "whseNbr": 7493, "onHand": 0, "inTransit": 0, "inWhse": 6, "onOrder": 0, "promDia": 0.02, "doh": 0.0, "agotado": 1, "falta1d": 1, "falta3d": 1, "falta7d": 1, "venta8sem": 1, "resurtible": "1"}, {"storeNbr": 3069, "storeName": "SC CABO SAN LUCAS", "storeType": "BASE STR Supercenter", "formato": "SUPERCENTER", "whseNbr": 7487, "onHand": 0, "inTransit": 6, "inWhse": 0, "onOrder": 0, "promDia": 0.02, "doh": 0.0, "agotado": 1, "falta1d": 1, "falta3d": 1, "falta7d": 1, "venta8sem": 1, "resurtible": "1"}, {"storeNbr": 3400, "storeName": "BA DELICIAS", "storeType": "BASE STR CF Bodega", "formato": "BODEGA", "whseNbr": 4924, "onHand": 0, "inTransit": 0, "inWhse": 0, "onOrder": 18, "promDia": 0.02, "doh": 0.0, "agotado": 1, "falta1d": 1, "falta3d": 1, "falta7d": 1, "venta8sem": 1, "resurtible": "1"}, {"storeNbr": 3486, "storeName": "BD SAN FRANCISCO URUAPAN", "storeType": "BASE STR CF Bodega", "formato": "BODEGA", "whseNbr": 7493, "onHand": 0, "inTransit": 0, "inWhse": 0, "onOrder": 6, "promDia": 0.02, "doh": 0.0, "agotado": 1, "falta1d": 1, "falta3d": 1, "falta7d": 1, "venta8sem": 1, "resurtible": "1"}, {"storeNbr": 3878, "storeName": "SC NINO OBRERO", "storeType": "BASE STR Supercenter", "formato": "SUPERCENTER", "whseNbr": 7493, "onHand": 0, "inTransit": 0, "inWhse": 6, "onOrder": 0, "promDia": 0.02, "doh": 0.0, "agotado": 1, "falta1d": 1, "falta3d": 1, "falta7d": 1, "venta8sem": 1, "resurtible": "1"}, {"storeNbr": 4066, "storeName": "BA BARRANCOS", "storeType": "BASE STR CF Bodega", "formato": "BODEGA", "whseNbr": 7487, "onHand": 0, "inTransit": 0, "inWhse": 0, "onOrder": 0, "promDia": 0.02, "doh": 0.0, "agotado": 1, "falta1d": 1, "falta3d": 1, "falta7d": 1, "venta8sem": 1, "resurtible": "1"}, {"storeNbr": 4568, "storeName": "BD RIO RAMOS ARIZPE", "storeType": "BASE STR CF Bodega", "formato": "BODEGA", "whseNbr": 7490, "onHand": 0, "inTransit": 0, "inWhse": 0, "onOrder": 6, "promDia": 0.02, "doh": 0.0, "agotado": 1, "falta1d": 1, "falta3d": 1, "falta7d": 1, "venta8sem": 1, "resurtible": "1"}, {"storeNbr": 4669, "storeName": "BD MUSARO", "storeType": "BASE STR CF Bodega", "formato": "BODEGA", "whseNbr": 7487, "onHand": 0, "inTransit": 0, "inWhse": 6, "onOrder": 6, "promDia": 0.02, "doh": 0.0, "agotado": 1, "falta1d": 1, "falta3d": 1, "falta7d": 1, "venta8sem": 1, "resurtible": "1"}, {"storeNbr": 5083, "storeName": "BD LOS HEROES MERIDA", "storeType": "BASE STR CF Bodega", "formato": "BODEGA", "whseNbr": 4188, "onHand": 0, "inTransit": 0, "inWhse": 0, "onOrder": 6, "promDia": 0.02, "doh": 0.0, "agotado": 1, "falta1d": 1, "falta3d": 1, "falta7d": 1, "venta8sem": 1, "resurtible": "1"}, {"storeNbr": 5196, "storeName": "MB PUEBLO NUEVO CENTRO", "storeType": "BASE STR CF Bodega", "formato": "MIBODEGA", "whseNbr": 5907, "onHand": 0, "inTransit": 0, "inWhse": 0, "onOrder": 6, "promDia": 0.02, "doh": 0.0, "agotado": 1, "falta1d": 1, "falta3d": 1, "falta7d": 1, "venta8sem": 1, "resurtible": "1"}, {"storeNbr": 5400, "storeName": "MB MAR DE CORTES", "storeType": "BASE STR CF Bodega", "formato": "MIBODEGA", "whseNbr": 4924, "onHand": 0, "inTransit": 0, "inWhse": 0, "onOrder": 12, "promDia": 0.02, "doh": 0.0, "agotado": 1, "falta1d": 1, "falta3d": 1, "falta7d": 1, "venta8sem": 1, "resurtible": "1"}, {"storeNbr": 6338, "storeName": "SC FRANCISCO VILLARREAL", "storeType": "BASE STR Supercenter", "formato": "SUPERCENTER", "whseNbr": 4640, "onHand": 0, "inTransit": 0, "inWhse": 0, "onOrder": 6, "promDia": 0.02, "doh": 0.0, "agotado": 1, "falta1d": 1, "falta3d": 1, "falta7d": 1, "venta8sem": 1, "resurtible": "1"}, {"storeNbr": 3770, "storeName": "BA PANTITLAN", "storeType": "BASE STR CF Bodega", "formato": "BODEGA", "whseNbr": 7471, "onHand": 1, "inTransit": 0, "inWhse": 0, "onOrder": 0, "promDia": 0.18, "doh": 5.6, "agotado": 0, "falta1d": 0, "falta3d": 0, "falta7d": 1, "venta8sem": 10, "resurtible": "1"}, {"storeNbr": 3632, "storeName": "SC CANCUN COMANCALCO", "storeType": "BASE STR Supercenter", "formato": "SUPERCENTER", "whseNbr": 4188, "onHand": 1, "inTransit": 0, "inWhse": 0, "onOrder": 12, "promDia": 0.16, "doh": 6.2, "agotado": 0, "falta1d": 0, "falta3d": 0, "falta7d": 1, "venta8sem": 9, "resurtible": "1"}, {"storeNbr": 1683, "storeName": "SC VICENTE GUERRERO", "storeType": "BASE STR Supercenter", "formato": "SUPERCENTER", "whseNbr": 7471, "onHand": 1, "inTransit": 0, "inWhse": 0, "onOrder": 6, "promDia": 0.12, "doh": 8.0, "agotado": 0, "falta1d": 0, "falta3d": 0, "falta7d": 0, "venta8sem": 7, "resurtible": "1"}, {"storeNbr": 2286, "storeName": "MB COBA TULUM", "storeType": "BASE STR CF Bodega", "formato": "MIBODEGA", "whseNbr": 4188, "onHand": 1, "inTransit": 0, "inWhse": 0, "onOrder": 6, "promDia": 0.12, "doh": 8.0, "agotado": 0, "falta1d": 0, "falta3d": 0, "falta7d": 0, "venta8sem": 7, "resurtible": "1"}, {"storeNbr": 3771, "storeName": "BA PLAZA CHURUBUSCO", "storeType": "BASE STR CF Bodega", "formato": "BODEGA", "whseNbr": 7482, "onHand": 1, "inTransit": 0, "inWhse": 0, "onOrder": 6, "promDia": 0.12, "doh": 8.0, "agotado": 0, "falta1d": 0, "falta3d": 0, "falta7d": 0, "venta8sem": 7, "resurtible": "1"}, {"storeNbr": 1104, "storeName": "BA TIZAYUCA", "storeType": "BASE STR CF Bodega", "formato": "BODEGA", "whseNbr": 7482, "onHand": 1, "inTransit": 0, "inWhse": 0, "onOrder": 0, "promDia": 0.11, "doh": 9.3, "agotado": 0, "falta1d": 0, "falta3d": 0, "falta7d": 0, "venta8sem": 6, "resurtible": "1"}, {"storeNbr": 1829, "storeName": "BA ALMOLOYA", "storeType": "BASE STR CF Bodega", "formato": "BODEGA", "whseNbr": 7494, "onHand": 1, "inTransit": 0, "inWhse": 0, "onOrder": 0, "promDia": 0.11, "doh": 9.3, "agotado": 0, "falta1d": 0, "falta3d": 0, "falta7d": 0, "venta8sem": 6, "resurtible": "1"}, {"storeNbr": 5352, "storeName": "SC GOMEZ PALACIO LAGUNA", "storeType": "BASE STR Supercenter", "formato": "SUPERCENTER", "whseNbr": 7490, "onHand": 1, "inTransit": 0, "inWhse": 0, "onOrder": 6, "promDia": 0.11, "doh": 9.3, "agotado": 0, "falta1d": 0, "falta3d": 0, "falta7d": 0, "venta8sem": 6, "resurtible": "1"}, {"storeNbr": 3806, "storeName": "BA RENACIMIENTO ACAPULCO", "storeType": "BASE STR CF Bodega", "formato": "BODEGA", "whseNbr": 7494, "onHand": 2, "inTransit": 0, "inWhse": 0, "onOrder": 6, "promDia": 0.2, "doh": 10.2, "agotado": 0, "falta1d": 0, "falta3d": 0, "falta7d": 0, "venta8sem": 11, "resurtible": "1"}, {"storeNbr": 5659, "storeName": "LA LADRILLERA", "storeType": "BASE STR CF Bodega", "formato": "BODEGA", "whseNbr": 7490, "onHand": 2, "inTransit": 0, "inWhse": 0, "onOrder": 6, "promDia": 0.2, "doh": 10.2, "agotado": 0, "falta1d": 0, "falta3d": 0, "falta7d": 0, "venta8sem": 11, "resurtible": "1"}, {"storeNbr": 3683, "storeName": "BA ESTADIO ANTIGUO", "storeType": "BASE STR CF Bodega", "formato": "BODEGA", "whseNbr": 7490, "onHand": 1, "inTransit": 0, "inWhse": 0, "onOrder": 0, "promDia": 0.09, "doh": 11.2, "agotado": 0, "falta1d": 0, "falta3d": 0, "falta7d": 0, "venta8sem": 5, "resurtible": "1"}, {"storeNbr": 3769, "storeName": "BA INSURGENTES - NORTE", "storeType": "BASE STR CF Bodega", "formato": "BODEGA", "whseNbr": 7494, "onHand": 1, "inTransit": 6, "inWhse": 0, "onOrder": 0, "promDia": 0.09, "doh": 11.2, "agotado": 0, "falta1d": 0, "falta3d": 0, "falta7d": 0, "venta8sem": 5, "resurtible": "1"}, {"storeNbr": 3805, "storeName": "BA SANTA LUCIA", "storeType": "BASE STR CF Bodega", "formato": "BODEGA", "whseNbr": 7482, "onHand": 1, "inTransit": 0, "inWhse": 0, "onOrder": 6, "promDia": 0.09, "doh": 11.2, "agotado": 0, "falta1d": 0, "falta3d": 0, "falta7d": 0, "venta8sem": 5, "resurtible": "1"}, {"storeNbr": 5624, "storeName": "BA VALLE SOLEADO", "storeType": "BASE STR CF Bodega", "formato": "BODEGA", "whseNbr": 7490, "onHand": 1, "inTransit": 0, "inWhse": 0, "onOrder": 6, "promDia": 0.09, "doh": 11.2, "agotado": 0, "falta1d": 0, "falta3d": 0, "falta7d": 0, "venta8sem": 5, "resurtible": "1"}, {"storeNbr": 3727, "storeName": "BA LOS TULIPANES", "storeType": "BASE STR CF Bodega", "formato": "BODEGA", "whseNbr": 7482, "onHand": 3, "inTransit": 0, "inWhse": 0, "onOrder": 12, "promDia": 0.25, "doh": 12.0, "agotado": 0, "falta1d": 0, "falta3d": 0, "falta7d": 0, "venta8sem": 14, "resurtible": "1"}, {"storeNbr": 3083, "storeName": "BD SAN ANDRES", "storeType": "BASE STR CF Bodega", "formato": "BODEGA", "whseNbr": 7490, "onHand": 2, "inTransit": 0, "inWhse": 0, "onOrder": 0, "promDia": 0.14, "doh": 14.0, "agotado": 0, "falta1d": 0, "falta3d": 0, "falta7d": 0, "venta8sem": 8, "resurtible": "1"}, {"storeNbr": 1834, "storeName": "SC PLAZA DEL LAGO", "storeType": "BASE STR Supercenter", "formato": "SUPERCENTER", "whseNbr": 7464, "onHand": 1, "inTransit": 0, "inWhse": 0, "onOrder": 6, "promDia": 0.07, "doh": 14.0, "agotado": 0, "falta1d": 0, "falta3d": 0, "falta7d": 0, "venta8sem": 4, "resurtible": "1"}, {"storeNbr": 3743, "storeName": "BA TULA", "storeType": "BASE STR CF Bodega", "formato": "BODEGA", "whseNbr": 7482, "onHand": 1, "inTransit": 0, "inWhse": 0, "onOrder": 12, "promDia": 0.07, "doh": 14.0, "agotado": 0, "falta1d": 0, "falta3d": 0, "falta7d": 0, "venta8sem": 4, "resurtible": "1"}, {"storeNbr": 3874, "storeName": "BA CANTIL", "storeType": "BASE STR CF Bodega", "formato": "BODEGA", "whseNbr": 7494, "onHand": 2, "inTransit": 0, "inWhse": 0, "onOrder": 0, "promDia": 0.11, "doh": 18.7, "agotado": 0, "falta1d": 0, "falta3d": 0, "falta7d": 0, "venta8sem": 6, "resurtible": "1"}, {"storeNbr": 2136, "storeName": "BA BOULEVARD MORELOS", "storeType": "BASE STR CF Bodega", "formato": "BODEGA", "whseNbr": 7494, "onHand": 1, "inTransit": 0, "inWhse": 0, "onOrder": 6, "promDia": 0.05, "doh": 18.7, "agotado": 0, "falta1d": 0, "falta3d": 0, "falta7d": 0, "venta8sem": 3, "resurtible": "1"}, {"storeNbr": 3778, "storeName": "BA XOCHIMILCO", "storeType": "BASE STR CF Bodega", "formato": "BODEGA", "whseNbr": 7494, "onHand": 1, "inTransit": 0, "inWhse": 0, "onOrder": 0, "promDia": 0.05, "doh": 18.7, "agotado": 0, "falta1d": 0, "falta3d": 0, "falta7d": 0, "venta8sem": 3, "resurtible": "1"}, {"storeNbr": 3786, "storeName": "BA SANTA FE", "storeType": "BASE STR CF Bodega", "formato": "BODEGA", "whseNbr": 7482, "onHand": 1, "inTransit": 0, "inWhse": 0, "onOrder": 6, "promDia": 0.05, "doh": 18.7, "agotado": 0, "falta1d": 0, "falta3d": 0, "falta7d": 0, "venta8sem": 3, "resurtible": "1"}, {"storeNbr": 4809, "storeName": "SC APODACA NORTE", "storeType": "BASE STR Supercenter", "formato": "SUPERCENTER", "whseNbr": 7490, "onHand": 1, "inTransit": 0, "inWhse": 0, "onOrder": 6, "promDia": 0.05, "doh": 18.7, "agotado": 0, "falta1d": 0, "falta3d": 0, "falta7d": 0, "venta8sem": 3, "resurtible": "1"}, {"storeNbr": 2459, "storeName": "BOD SOLIDARIDAD IRAPUATO", "storeType": "BASE STR CF Bodega", "formato": "BODEGA", "whseNbr": 7494, "onHand": 5, "inTransit": 0, "inWhse": 0, "onOrder": 6, "promDia": 0.25, "doh": 20.0, "agotado": 0, "falta1d": 0, "falta3d": 0, "falta7d": 0, "venta8sem": 14, "resurtible": "1"}, {"storeNbr": 3146, "storeName": "BA CHAVENA JUAREZ", "storeType": "BASE STR CF Bodega", "formato": "BODEGA", "whseNbr": 4640, "onHand": 4, "inTransit": 0, "inWhse": 0, "onOrder": 12, "promDia": 0.2, "doh": 20.4, "agotado": 0, "falta1d": 0, "falta3d": 0, "falta7d": 0, "venta8sem": 11, "resurtible": "1"}, {"storeNbr": 3121, "storeName": "BA YAUTEPEC", "storeType": "BASE STR CF Bodega", "formato": "BODEGA", "whseNbr": 7471, "onHand": 7, "inTransit": 0, "inWhse": 0, "onOrder": 6, "promDia": 0.34, "doh": 20.6, "agotado": 0, "falta1d": 0, "falta3d": 0, "falta7d": 0, "venta8sem": 19, "resurtible": "1"}, {"storeNbr": 2698, "storeName": "MB PRADERA DORADA", "storeType": "BASE STR CF Bodega", "formato": "MIBODEGA", "whseNbr": 7487, "onHand": 3, "inTransit": 0, "inWhse": 0, "onOrder": 6, "promDia": 0.14, "doh": 21.0, "agotado": 0, "falta1d": 0, "falta3d": 0, "falta7d": 0, "venta8sem": 8, "resurtible": "1"}, {"storeNbr": 3227, "storeName": "BD TUXPAN CENTRO", "storeType": "BASE STR CF Bodega", "formato": "BODEGA", "whseNbr": 7494, "onHand": 4, "inTransit": 0, "inWhse": 0, "onOrder": 12, "promDia": 0.18, "doh": 22.4, "agotado": 0, "falta1d": 0, "falta3d": 0, "falta7d": 0, "venta8sem": 10, "resurtible": "1"}, {"storeNbr": 3871, "storeName": "BA PLAZA CUAUTITLAN", "storeType": "BASE STR CF Bodega", "formato": "BODEGA", "whseNbr": 7494, "onHand": 3, "inTransit": 0, "inWhse": 0, "onOrder": 6, "promDia": 0.12, "doh": 24.0, "agotado": 0, "falta1d": 0, "falta3d": 0, "falta7d": 0, "venta8sem": 7, "resurtible": "1"}, {"storeNbr": 3000, "storeName": "BA TAXCO LIBRAMIENTO", "storeType": "BASE STR CF Bodega", "formato": "BODEGA", "whseNbr": 7494, "onHand": 4, "inTransit": 0, "inWhse": 0, "onOrder": 6, "promDia": 0.16, "doh": 24.9, "agotado": 0, "falta1d": 0, "falta3d": 0, "falta7d": 0, "venta8sem": 9, "resurtible": "1"}, {"storeNbr": 3443, "storeName": "BA CLOUTHIER", "storeType": "BASE STR CF Bodega", "formato": "BODEGA", "whseNbr": 7490, "onHand": 5, "inTransit": 0, "inWhse": 0, "onOrder": 6, "promDia": 0.18, "doh": 28.0, "agotado": 0, "falta1d": 0, "falta3d": 0, "falta7d": 0, "venta8sem": 10, "resurtible": "1"}, {"storeNbr": 2383, "storeName": "SC MERIDA", "storeType": "BASE STR Supercenter", "formato": "SUPERCENTER", "whseNbr": 4188, "onHand": 4, "inTransit": 0, "inWhse": 0, "onOrder": 6, "promDia": 0.14, "doh": 28.0, "agotado": 0, "falta1d": 0, "falta3d": 0, "falta7d": 0, "venta8sem": 8, "resurtible": "1"}, {"storeNbr": 2993, "storeName": "BA CAMINO A TLALTEPANGO", "storeType": "BASE STR CF Bodega", "formato": "BODEGA", "whseNbr": 7471, "onHand": 4, "inTransit": 0, "inWhse": 0, "onOrder": 6, "promDia": 0.14, "doh": 28.0, "agotado": 0, "falta1d": 0, "falta3d": 0, "falta7d": 0, "venta8sem": 8, "resurtible": "1"}, {"storeNbr": 3897, "storeName": "BA LA VIRGEN", "storeType": "BASE STR CF Bodega", "formato": "BODEGA", "whseNbr": 7471, "onHand": 4, "inTransit": 0, "inWhse": 0, "onOrder": 6, "promDia": 0.14, "doh": 28.0, "agotado": 0, "falta1d": 0, "falta3d": 0, "falta7d": 0, "venta8sem": 8, "resurtible": "1"}, {"storeNbr": 383, "storeName": "SC PUERTA TLATELOLCO", "storeType": "BASE STR Supercenter", "formato": "SUPERCENTER", "whseNbr": 7464, "onHand": 3, "inTransit": 0, "inWhse": 0, "onOrder": 6, "promDia": 0.11, "doh": 28.0, "agotado": 0, "falta1d": 0, "falta3d": 0, "falta7d": 0, "venta8sem": 6, "resurtible": "1"}, {"storeNbr": 3630, "storeName": "SC LAS ADELITAS", "storeType": "BASE STR Supercenter", "formato": "SUPERCENTER", "whseNbr": 7490, "onHand": 3, "inTransit": 0, "inWhse": 0, "onOrder": 6, "promDia": 0.11, "doh": 28.0, "agotado": 0, "falta1d": 0, "falta3d": 0, "falta7d": 0, "venta8sem": 6, "resurtible": "1"}, {"storeNbr": 4635, "storeName": "MB ZACATLAN NORTE", "storeType": "BASE STR CF Bodega", "formato": "MIBODEGA", "whseNbr": 8805, "onHand": 3, "inTransit": 0, "inWhse": 0, "onOrder": 6, "promDia": 0.11, "doh": 28.0, "agotado": 0, "falta1d": 0, "falta3d": 0, "falta7d": 0, "venta8sem": 6, "resurtible": "1"}, {"storeNbr": 5427, "storeName": "MB MATIAS ROMERO", "storeType": "BASE STR CF Bodega", "formato": "MIBODEGA", "whseNbr": 7468, "onHand": 3, "inTransit": 0, "inWhse": 6, "onOrder": 12, "promDia": 0.11, "doh": 28.0, "agotado": 0, "falta1d": 0, "falta3d": 0, "falta7d": 0, "venta8sem": 6, "resurtible": "1"}, {"storeNbr": 3756, "storeName": "BA TLALNEPANTLA", "storeType": "BASE STR CF Bodega", "formato": "BODEGA", "whseNbr": 7482, "onHand": 2, "inTransit": 0, "inWhse": 0, "onOrder": 12, "promDia": 0.07, "doh": 28.0, "agotado": 0, "falta1d": 0, "falta3d": 0, "falta7d": 0, "venta8sem": 4, "resurtible": "1"}, {"storeNbr": 5430, "storeName": "MB PONCITLAN", "storeType": "BASE STR CF Bodega", "formato": "MIBODEGA", "whseNbr": 5907, "onHand": 2, "inTransit": 0, "inWhse": 0, "onOrder": 12, "promDia": 0.07, "doh": 28.0, "agotado": 0, "falta1d": 0, "falta3d": 0, "falta7d": 0, "venta8sem": 4, "resurtible": "1"}, {"storeNbr": 1590, "storeName": "BA CASAS GRANDES", "storeType": "BASE STR CF Bodega", "formato": "BODEGA", "whseNbr": 4640, "onHand": 8, "inTransit": 0, "inWhse": 0, "onOrder": 0, "promDia": 0.25, "doh": 32.0, "agotado": 0, "falta1d": 0, "falta3d": 0, "falta7d": 0, "venta8sem": 14, "resurtible": "1"}, {"storeNbr": 3752, "storeName": "BA VALLEJO", "storeType": "BASE STR CF Bodega", "formato": "BODEGA", "whseNbr": 7482, "onHand": 4, "inTransit": 0, "inWhse": 0, "onOrder": 12, "promDia": 0.12, "doh": 32.0, "agotado": 0, "falta1d": 0, "falta3d": 0, "falta7d": 0, "venta8sem": 7, "resurtible": "1"}, {"storeNbr": 1897, "storeName": "BA S CRISTOBAL D L CASAS", "storeType": "BASE STR CF Bodega", "formato": "BODEGA", "whseNbr": 7468, "onHand": 6, "inTransit": 0, "inWhse": 0, "onOrder": 12, "promDia": 0.18, "doh": 33.6, "agotado": 0, "falta1d": 0, "falta3d": 0, "falta7d": 0, "venta8sem": 10, "resurtible": "1"}, {"storeNbr": 5700, "storeName": "SC MEXICO 68", "storeType": "BASE STR Supercenter", "formato": "SUPERCENTER", "whseNbr": 7487, "onHand": 6, "inTransit": 0, "inWhse": 0, "onOrder": 6, "promDia": 0.18, "doh": 33.6, "agotado": 0, "falta1d": 0, "falta3d": 0, "falta7d": 0, "venta8sem": 10, "resurtible": "1"}, {"storeNbr": 1110, "storeName": "BA PLAZA ECATEPEC", "storeType": "BASE STR CF Bodega", "formato": "BODEGA", "whseNbr": 7482, "onHand": 6, "inTransit": 0, "inWhse": 0, "onOrder": 0, "promDia": 0.16, "doh": 37.3, "agotado": 0, "falta1d": 0, "falta3d": 0, "falta7d": 0, "venta8sem": 9, "resurtible": "1"}, {"storeNbr": 2463, "storeName": "SC VERACRUZ", "storeType": "BASE STR Supercenter", "formato": "SUPERCENTER", "whseNbr": 7471, "onHand": 6, "inTransit": 0, "inWhse": 0, "onOrder": 0, "promDia": 0.16, "doh": 37.3, "agotado": 0, "falta1d": 0, "falta3d": 0, "falta7d": 0, "venta8sem": 9, "resurtible": "1"}, {"storeNbr": 3216, "storeName": "BA JESUS MARIA II", "storeType": "BASE STR CF Bodega", "formato": "BODEGA", "whseNbr": 7493, "onHand": 6, "inTransit": 0, "inWhse": 0, "onOrder": 0, "promDia": 0.16, "doh": 37.3, "agotado": 0, "falta1d": 0, "falta3d": 0, "falta7d": 0, "venta8sem": 9, "resurtible": "1"}, {"storeNbr": 3792, "storeName": "BA SAN JUANICO", "storeType": "BASE STR CF Bodega", "formato": "BODEGA", "whseNbr": 7482, "onHand": 4, "inTransit": 0, "inWhse": 0, "onOrder": 0, "promDia": 0.11, "doh": 37.3, "agotado": 0, "falta1d": 0, "falta3d": 0, "falta7d": 0, "venta8sem": 6, "resurtible": ""}, {"storeNbr": 3845, "storeName": "SC UNIVERSIDAD", "storeType": "BASE STR Supercenter", "formato": "SUPERCENTER", "whseNbr": 7471, "onHand": 4, "inTransit": 0, "inWhse": 0, "onOrder": 6, "promDia": 0.11, "doh": 37.3, "agotado": 0, "falta1d": 0, "falta3d": 0, "falta7d": 0, "venta8sem": 6, "resurtible": "1"}, {"storeNbr": 3020, "storeName": "BA XALOSTOC", "storeType": "BASE STR CF Bodega", "formato": "BODEGA", "whseNbr": 7482, "onHand": 2, "inTransit": 0, "inWhse": 0, "onOrder": 6, "promDia": 0.05, "doh": 37.3, "agotado": 0, "falta1d": 0, "falta3d": 0, "falta7d": 0, "venta8sem": 3, "resurtible": "1"}, {"storeNbr": 1580, "storeName": "SC EL ROSARIO", "storeType": "BASE STR Supercenter", "formato": "SUPERCENTER", "whseNbr": 7464, "onHand": 14, "inTransit": 0, "inWhse": 0, "onOrder": 0, "promDia": 0.34, "doh": 41.3, "agotado": 0, "falta1d": 0, "falta3d": 0, "falta7d": 0, "venta8sem": 19, "resurtible": "1"}, {"storeNbr": 3071, "storeName": "SC FRANCISCO VILLA", "storeType": "BASE STR Supercenter", "formato": "SUPERCENTER", "whseNbr": 7487, "onHand": 9, "inTransit": 0, "inWhse": 0, "onOrder": 0, "promDia": 0.21, "doh": 42.0, "agotado": 0, "falta1d": 0, "falta3d": 0, "falta7d": 0, "venta8sem": 12, "resurtible": "1"}, {"storeNbr": 2106, "storeName": "BA LAS PALMAS", "storeType": "BASE STR CF Bodega", "formato": "BODEGA", "whseNbr": 7487, "onHand": 3, "inTransit": 0, "inWhse": 0, "onOrder": 6, "promDia": 0.07, "doh": 42.0, "agotado": 0, "falta1d": 0, "falta3d": 0, "falta7d": 0, "venta8sem": 4, "resurtible": "1"}, {"storeNbr": 2954, "storeName": "BD EL DORADO TULTEPEC", "storeType": "BASE STR CF Bodega", "formato": "BODEGA", "whseNbr": 7482, "onHand": 5, "inTransit": 0, "inWhse": 0, "onOrder": 0, "promDia": 0.11, "doh": 46.7, "agotado": 0, "falta1d": 0, "falta3d": 0, "falta7d": 0, "venta8sem": 6, "resurtible": "1"}, {"storeNbr": 4549, "storeName": "SC LOS MOCHIS", "storeType": "BASE STR Supercenter", "formato": "SUPERCENTER", "whseNbr": 7487, "onHand": 7, "inTransit": 0, "inWhse": 0, "onOrder": 0, "promDia": 0.14, "doh": 49.0, "agotado": 0, "falta1d": 0, "falta3d": 0, "falta7d": 0, "venta8sem": 8, "resurtible": "1"}, {"storeNbr": 3085, "storeName": "MB RIO GRANDE", "storeType": "BASE STR CF Bodega", "formato": "MIBODEGA", "whseNbr": 5922, "onHand": 16, "inTransit": 0, "inWhse": 0, "onOrder": 0, "promDia": 0.29, "doh": 56.0, "agotado": 0, "falta1d": 0, "falta3d": 0, "falta7d": 0, "venta8sem": 16, "resurtible": "1"}, {"storeNbr": 3798, "storeName": "BA SANTA CECILIA", "storeType": "BASE STR CF Bodega", "formato": "BODEGA", "whseNbr": 7482, "onHand": 8, "inTransit": 0, "inWhse": 0, "onOrder": 0, "promDia": 0.14, "doh": 56.0, "agotado": 0, "falta1d": 0, "falta3d": 0, "falta7d": 0, "venta8sem": 8, "resurtible": "1"}, {"storeNbr": 1767, "storeName": "BA PUERTO DE PALOS", "storeType": "BASE STR CF Bodega", "formato": "BODEGA", "whseNbr": 4640, "onHand": 7, "inTransit": 0, "inWhse": 0, "onOrder": 0, "promDia": 0.12, "doh": 56.0, "agotado": 0, "falta1d": 0, "falta3d": 0, "falta7d": 0, "venta8sem": 7, "resurtible": "1"}, {"storeNbr": 3872, "storeName": "SC BALBUENA", "storeType": "BASE STR Supercenter", "formato": "SUPERCENTER", "whseNbr": 7471, "onHand": 7, "inTransit": 0, "inWhse": 0, "onOrder": 0, "promDia": 0.12, "doh": 56.0, "agotado": 0, "falta1d": 0, "falta3d": 0, "falta7d": 0, "venta8sem": 7, "resurtible": "1"}, {"storeNbr": 4547, "storeName": "SC PLAZA EDUARDO MOLINA", "storeType": "BASE STR Supercenter", "formato": "SUPERCENTER", "whseNbr": 7464, "onHand": 7, "inTransit": 0, "inWhse": 0, "onOrder": 0, "promDia": 0.12, "doh": 56.0, "agotado": 0, "falta1d": 0, "falta3d": 0, "falta7d": 0, "venta8sem": 7, "resurtible": "1"}, {"storeNbr": 5398, "storeName": "MB BERMEJILLO", "storeType": "BASE STR CF Bodega", "formato": "MIBODEGA", "whseNbr": 5922, "onHand": 7, "inTransit": 0, "inWhse": 0, "onOrder": 0, "promDia": 0.12, "doh": 56.0, "agotado": 0, "falta1d": 0, "falta3d": 0, "falta7d": 0, "venta8sem": 7, "resurtible": "1"}, {"storeNbr": 1400, "storeName": "BA JOYAS DE COACALCO", "storeType": "BASE STR CF Bodega", "formato": "BODEGA", "whseNbr": 7494, "onHand": 6, "inTransit": 0, "inWhse": 0, "onOrder": 0, "promDia": 0.11, "doh": 56.0, "agotado": 0, "falta1d": 0, "falta3d": 0, "falta7d": 0, "venta8sem": 6, "resurtible": "1"}, {"storeNbr": 2006, "storeName": "BA JUCHITAN", "storeType": "BASE STR CF Bodega", "formato": "BODEGA", "whseNbr": 7468, "onHand": 5, "inTransit": 0, "inWhse": 0, "onOrder": 6, "promDia": 0.09, "doh": 56.0, "agotado": 0, "falta1d": 0, "falta3d": 0, "falta7d": 0, "venta8sem": 5, "resurtible": "1"}, {"storeNbr": 3914, "storeName": "BA CONSTITUYENTES", "storeType": "BASE STR CF Bodega", "formato": "BODEGA", "whseNbr": 7494, "onHand": 5, "inTransit": 0, "inWhse": 0, "onOrder": 6, "promDia": 0.09, "doh": 56.0, "agotado": 0, "falta1d": 0, "falta3d": 0, "falta7d": 0, "venta8sem": 5, "resurtible": "1"}, {"storeNbr": 1109, "storeName": "BA AYOTLA", "storeType": "BASE STR CF Bodega", "formato": "BODEGA", "whseNbr": 7471, "onHand": 4, "inTransit": 0, "inWhse": 0, "onOrder": 6, "promDia": 0.07, "doh": 56.0, "agotado": 0, "falta1d": 0, "falta3d": 0, "falta7d": 0, "venta8sem": 4, "resurtible": "1"}, {"storeNbr": 1561, "storeName": "BA VALLE HERMOSO", "storeType": "BASE STR CF Bodega", "formato": "BODEGA", "whseNbr": 7490, "onHand": 4, "inTransit": 0, "inWhse": 0, "onOrder": 0, "promDia": 0.07, "doh": 56.0, "agotado": 0, "falta1d": 0, "falta3d": 0, "falta7d": 0, "venta8sem": 4, "resurtible": "1"}, {"storeNbr": 1841, "storeName": "BA PLAN DE AYALA", "storeType": "BASE STR CF Bodega", "formato": "BODEGA", "whseNbr": 7471, "onHand": 4, "inTransit": 0, "inWhse": 0, "onOrder": 6, "promDia": 0.07, "doh": 56.0, "agotado": 0, "falta1d": 0, "falta3d": 0, "falta7d": 0, "venta8sem": 4, "resurtible": "1"}, {"storeNbr": 2648, "storeName": "SC PLAZA EL PASEO", "storeType": "BASE STR Supercenter", "formato": "SUPERCENTER", "whseNbr": 7471, "onHand": 4, "inTransit": 0, "inWhse": 0, "onOrder": 6, "promDia": 0.07, "doh": 56.0, "agotado": 0, "falta1d": 0, "falta3d": 0, "falta7d": 0, "venta8sem": 4, "resurtible": "1"}, {"storeNbr": 4137, "storeName": "SC CHAPULTEPEC", "storeType": "BASE STR Supercenter", "formato": "SUPERCENTER", "whseNbr": 7490, "onHand": 4, "inTransit": 0, "inWhse": 0, "onOrder": 6, "promDia": 0.07, "doh": 56.0, "agotado": 0, "falta1d": 0, "falta3d": 0, "falta7d": 0, "venta8sem": 4, "resurtible": "1"}, {"storeNbr": 1057, "storeName": "BA CHILPANCINGO", "storeType": "BASE STR CF Bodega", "formato": "BODEGA", "whseNbr": 7471, "onHand": 3, "inTransit": 0, "inWhse": 0, "onOrder": 18, "promDia": 0.05, "doh": 56.0, "agotado": 0, "falta1d": 0, "falta3d": 0, "falta7d": 0, "venta8sem": 3, "resurtible": "1"}, {"storeNbr": 5112, "storeName": "SC PETEMPICH", "storeType": "BASE STR Supercenter", "formato": "SUPERCENTER", "whseNbr": 4188, "onHand": 3, "inTransit": 0, "inWhse": 0, "onOrder": 6, "promDia": 0.05, "doh": 56.0, "agotado": 0, "falta1d": 0, "falta3d": 0, "falta7d": 0, "venta8sem": 3, "resurtible": "1"}, {"storeNbr": 1494, "storeName": "BA ACAMBARO", "storeType": "BASE STR CF Bodega", "formato": "BODEGA", "whseNbr": 7494, "onHand": 2, "inTransit": 0, "inWhse": 0, "onOrder": 0, "promDia": 0.04, "doh": 56.0, "agotado": 0, "falta1d": 0, "falta3d": 0, "falta7d": 0, "venta8sem": 2, "resurtible": ""}, {"storeNbr": 2055, "storeName": "MB ZACATLAN", "storeType": "BASE STR CF Bodega", "formato": "MIBODEGA", "whseNbr": 8805, "onHand": 2, "inTransit": 0, "inWhse": 0, "onOrder": 6, "promDia": 0.04, "doh": 56.0, "agotado": 0, "falta1d": 0, "falta3d": 0, "falta7d": 0, "venta8sem": 2, "resurtible": "1"}, {"storeNbr": 3760, "storeName": "BA LOMAS ESTRELLA", "storeType": "BASE STR CF Bodega", "formato": "BODEGA", "whseNbr": 7494, "onHand": 2, "inTransit": 0, "inWhse": 0, "onOrder": 6, "promDia": 0.04, "doh": 56.0, "agotado": 0, "falta1d": 0, "falta3d": 0, "falta7d": 0, "venta8sem": 2, "resurtible": "1"}, {"storeNbr": 1870, "storeName": "BA TEPOTZOTLAN", "storeType": "BASE STR CF Bodega", "formato": "BODEGA", "whseNbr": 7482, "onHand": 1, "inTransit": 0, "inWhse": 0, "onOrder": 6, "promDia": 0.02, "doh": 56.0, "agotado": 0, "falta1d": 0, "falta3d": 0, "falta7d": 0, "venta8sem": 1, "resurtible": "1"}, {"storeNbr": 2471, "storeName": "MB LERDO DE TEJADA", "storeType": "BASE STR CF Bodega", "formato": "MIBODEGA", "whseNbr": 7468, "onHand": 1, "inTransit": 0, "inWhse": 6, "onOrder": 0, "promDia": 0.02, "doh": 56.0, "agotado": 0, "falta1d": 0, "falta3d": 0, "falta7d": 0, "venta8sem": 1, "resurtible": "1"}, {"storeNbr": 3026, "storeName": "BA GOBERNADORA", "storeType": "BASE STR CF Bodega", "formato": "BODEGA", "whseNbr": 7482, "onHand": 1, "inTransit": 0, "inWhse": 0, "onOrder": 6, "promDia": 0.02, "doh": 56.0, "agotado": 0, "falta1d": 0, "falta3d": 0, "falta7d": 0, "venta8sem": 1, "resurtible": "1"}, {"storeNbr": 3040, "storeName": "BA JUAN PABLO II", "storeType": "BASE STR CF Bodega", "formato": "BODEGA", "whseNbr": 4188, "onHand": 1, "inTransit": 0, "inWhse": 0, "onOrder": 12, "promDia": 0.02, "doh": 56.0, "agotado": 0, "falta1d": 0, "falta3d": 0, "falta7d": 0, "venta8sem": 1, "resurtible": "1"}, {"storeNbr": 5232, "storeName": "BD LOS REYES PLAZA", "storeType": "BASE STR CF Bodega", "formato": "BODEGA", "whseNbr": 7493, "onHand": 1, "inTransit": 0, "inWhse": 0, "onOrder": 6, "promDia": 0.02, "doh": 56.0, "agotado": 0, "falta1d": 0, "falta3d": 0, "falta7d": 0, "venta8sem": 1, "resurtible": "1"}, {"storeNbr": 4703, "storeName": "BD CABO MIRAMAR", "storeType": "BASE STR CF Bodega", "formato": "BODEGA", "whseNbr": 7487, "onHand": 24, "inTransit": 0, "inWhse": 0, "onOrder": 0, "promDia": 0.41, "doh": 58.4, "agotado": 0, "falta1d": 0, "falta3d": 0, "falta7d": 0, "venta8sem": 23, "resurtible": "1"}, {"storeNbr": 1655, "storeName": "MB JALTENANGO", "storeType": "BASE STR CF Bodega", "formato": "MIBODEGA", "whseNbr": 7468, "onHand": 17, "inTransit": 0, "inWhse": 0, "onOrder": 0, "promDia": 0.29, "doh": 59.5, "agotado": 0, "falta1d": 0, "falta3d": 0, "falta7d": 0, "venta8sem": 16, "resurtible": "1"}, {"storeNbr": 1032, "storeName": "SC LOMAS VERDES", "storeType": "BASE STR Supercenter", "formato": "SUPERCENTER", "whseNbr": 7464, "onHand": 7, "inTransit": 0, "inWhse": 0, "onOrder": 0, "promDia": 0.11, "doh": 65.3, "agotado": 0, "falta1d": 0, "falta3d": 0, "falta7d": 0, "venta8sem": 6, "resurtible": "1"}, {"storeNbr": 5608, "storeName": "MB MAGDALENA", "storeType": "BASE STR CF Bodega", "formato": "MIBODEGA", "whseNbr": 5907, "onHand": 7, "inTransit": 0, "inWhse": 0, "onOrder": 6, "promDia": 0.11, "doh": 65.3, "agotado": 0, "falta1d": 0, "falta3d": 0, "falta7d": 0, "venta8sem": 6, "resurtible": "1"}, {"storeNbr": 1125, "storeName": "MB IXMIQUILPAN", "storeType": "BASE STR CF Bodega", "formato": "MIBODEGA", "whseNbr": 8805, "onHand": 6, "inTransit": 0, "inWhse": 0, "onOrder": 6, "promDia": 0.09, "doh": 67.2, "agotado": 0, "falta1d": 0, "falta3d": 0, "falta7d": 0, "venta8sem": 5, "resurtible": "1"}, {"storeNbr": 2875, "storeName": "MB COATZINTLA", "storeType": "BASE STR CF Bodega", "formato": "MIBODEGA", "whseNbr": 8805, "onHand": 6, "inTransit": 0, "inWhse": 0, "onOrder": 0, "promDia": 0.09, "doh": 67.2, "agotado": 0, "falta1d": 0, "falta3d": 0, "falta7d": 0, "venta8sem": 5, "resurtible": "1"}, {"storeNbr": 5088, "storeName": "MB TOLIMAN", "storeType": "BASE STR CF Bodega", "formato": "MIBODEGA", "whseNbr": 8805, "onHand": 6, "inTransit": 0, "inWhse": 0, "onOrder": 0, "promDia": 0.09, "doh": 67.2, "agotado": 0, "falta1d": 0, "falta3d": 0, "falta7d": 0, "venta8sem": 5, "resurtible": "1"}]}